styles/__init__.py
ys_tester/__init__.py
ys_tester/ys_tester.py
ys_tester_yubarajshrestha-0.0.1.dist-info/LICENSE
ys_tester_yubarajshrestha-0.0.1.dist-info/METADATA
ys_tester_yubarajshrestha-0.0.1.dist-info/WHEEL
ys_tester_yubarajshrestha-0.0.1.dist-info/top_level.txt
ys_tester_yubarajshrestha-0.0.1.dist-info/RECORD
